Metadata-Version: 2.1
Name: eros-api
Version: 0.0.1
Summary: A package for Pulling data from all social media platforms
Home-page: https://github.com/cop-discord/eros
Download-URL: https://github.com/cop-discord/eros
Author: cop
Author-email: cop-discord <cop@catgir.ls>
Project-URL: Homepage, https://github.com/cop-discord/eros
Project-URL: Issues, https://github.com/cop-discord/eros/issues
Classifier: Programming Language :: Python :: 3
Classifier: License :: OSI Approved :: MIT License
Classifier: Operating System :: OS Independent
Requires-Python: >=3.6
